hanzo_tools/__init__.py
hanzo_tools/shell/__init__.py
hanzo_tools/shell/base_process.py
hanzo_tools/shell/dag_tool.py
hanzo_tools/shell/npx_tool.py
hanzo_tools/shell/open_tool.py
hanzo_tools/shell/ps_tool.py
hanzo_tools/shell/truncate.py
hanzo_tools/shell/uvx_tool.py
hanzo_tools/shell/zsh_tool.py
hanzo_tools_shell-0.2.0.dist-info/METADATA
hanzo_tools_shell-0.2.0.dist-info/WHEEL
hanzo_tools_shell-0.2.0.dist-info/entry_points.txt
hanzo_tools_shell-0.2.0.dist-info/top_level.txt
hanzo_tools_shell-0.2.0.dist-info/RECORD
