Metadata-Version: 2.4
Name: hanzo-tools-shell
Version: 0.2.0
Summary: Shell/command execution tools - dag, ps, zsh, npx, uvx, open
Author-email: Hanzo Industries Inc <dev@hanzo.ai>
License: MIT
Keywords: hanzo,tools,shell,mcp,ai,dag,zsh
Requires-Python: >=3.12
Requires-Dist: hanzo-tools-core>=0.1.0
Requires-Dist: mcp>=1.25.0
Requires-Dist: pydantic>=2.12.5
Requires-Dist: aiofiles>=24.0.0
Requires-Dist: tiktoken>=0.8.0
